calvinhobbes_get.py
setup.py
calvin_hobbes_get.egg-info/PKG-INFO
calvin_hobbes_get.egg-info/SOURCES.txt
calvin_hobbes_get.egg-info/dependency_links.txt
calvin_hobbes_get.egg-info/entry_points.txt
calvin_hobbes_get.egg-info/not-zip-safe
calvin_hobbes_get.egg-info/requires.txt
calvin_hobbes_get.egg-info/top_level.txt