Metadata-Version: 1.1
Name: calvin-hobbes-get
Version: 0.0.1
Summary: downloader of calvin and hobbes comics
Home-page: https://github.com/tiagocoutinho/calvin-hobbes
Author: Tiago Coutinho
Author-email: coutinhotiago@gmail.com
License: UNKNOWN
Keywords: calvin,hobbes
Platform: UNKNOWN
Classifier: Programming Language :: Python :: 2.6
Classifier: Programming Language :: Python :: 2.7
Classifier: Programming Language :: Python :: 3.4
Classifier: Programming Language :: Python :: 3.5
Classifier: Programming Language :: Python :: 3.6
